{"code":200,"data":{"area":211.62618677628052,"image":"https://file.greensketch.ai/maps/au/sale_agent/image/metromap_latest/image_115.9969478_-31.783909.jpg","flip_corrected_rotation_euler":[-179.8694305419922,-88.72989654541016,0.13391919434070587],"center":"115.9969478,-31.783909","model_offset":[3.1749320328235626,1.27761444542557],"box_max_length":28.944211597694895,"rotation_euler":[0.1305750012397766,88.7302017211914,-0.1339195817708969],"image_clipped":"https://file.greensketch.ai/maps/au/sale_agent/image/metromap_latest/image_115.9969478_-31.783909_clip.jpg","map_type":"metromap_latest","model":"https://file.greensketch.ai/oswai/prod/sam3d/540d05f6-ded2-48b8-8904-7e254eaf16b7.glb","with_pv":false,"is_old":false,"image_drawed":"https://file.greensketch.ai/maps/au/sale_agent/image/metromap_latest/image_115.9969478_-31.783909_drawed.jpg","status":"completed"},"msg":"success"}