{"code":200,"data":{"area":227.226131125557,"image":"https://file.greensketch.ai/maps/au/sale_agent/image/metromap_latest/image_145.6892458_-16.8814334.jpg","flip_corrected_rotation_euler":[0.15222059190273285,84.26920318603516,179.85617065429688],"center":"145.6892458,-16.8814334","model_offset":[-3.371669288724661,2.5478171908762306],"box_max_length":21.988304088228254,"rotation_euler":[-179.84779357910156,-84.26923370361328,-179.85617065429688],"image_clipped":"https://file.greensketch.ai/maps/au/sale_agent/image/metromap_latest/image_145.6892458_-16.8814334_clip.jpg","map_type":"metromap_latest","model":"https://file.greensketch.ai/oswai/prod/sam3d/f95027fb-bb3f-4d95-89d7-a4d6a1c6b934.glb","with_pv":true,"is_old":false,"image_drawed":"https://file.greensketch.ai/maps/au/sale_agent/image/metromap_latest/image_145.6892458_-16.8814334_drawed.jpg","status":"completed"},"msg":"success"}