{"code":200,"data":{"area":334.5107837948017,"image":"https://file.greensketch.ai/maps/au/sale_agent/image/metromap_latest/image_152.9273219_-27.6729964.jpg","flip_corrected_rotation_euler":[2.6966919540427625E-4,-31.311613082885742,-179.99911499023438],"center":"152.9273219,-27.6729964","model_offset":[0.8108021840453148,2.822439036797732],"box_max_length":27.760761481684796,"rotation_euler":[-179.99974060058594,31.31161880493164,179.99911499023438],"image_clipped":"https://file.greensketch.ai/maps/au/sale_agent/image/metromap_latest/image_152.9273219_-27.6729964_clip.jpg","map_type":"metromap_latest","model":"https://file.greensketch.ai/oswai/prod/sam3d/554866e2-9c7f-431b-9189-095d4bb17c10.glb","with_pv":true,"is_old":false,"image_drawed":"https://file.greensketch.ai/maps/au/sale_agent/image/metromap_latest/image_152.9273219_-27.6729964_drawed.jpg","status":"completed"},"msg":"success"}